{
  "generator-jhipster": {
    "promptValues": {
      "packageName": "com.crumbsandcream"
    },
    "jhipsterVersion": "5.1.0",
    "applicationType": "monolith",
    "baseName": "crumbsandcream",
    "packageName": "com.crumbsandcream",
    "packageFolder": "com/crumbsandcream",
    "serverPort": "8080",
    "authenticationType": "jwt",
    "cacheProvider": "hazelcast",
    "enableHibernateCache": false,
    "websocket": false,
    "databaseType": "mongodb",
    "devDatabaseType": "mongodb",
    "prodDatabaseType": "mongodb",
    "searchEngine": false,
    "messageBroker": false,
    "serviceDiscoveryType": false,
    "buildTool": "maven",
    "enableSwaggerCodegen": false,
    "jwtSecretKey": "ee71432742c65e0f1c312c2ae252729ecb195b19",
    "clientFramework": "angularX",
    "useSass": true,
    "clientPackageManager": "yarn",
    "testFrameworks": [],
    "jhiPrefix": "jhi",
    "enableTranslation": false
  }
}